opsmodelviewer.py
opsmodelviewer-1.2.0.dist-info/METADATA
opsmodelviewer-1.2.0.dist-info/WHEEL
opsmodelviewer-1.2.0.dist-info/entry_points.txt
opsmodelviewer-1.2.0.dist-info/top_level.txt
opsmodelviewer-1.2.0.dist-info/RECORD
