Metadata-Version: 2.1
Name: opsmodelviewer
Version: 1.2.0
Summary: A viewer for 2D OpenSees models.
Home-page: https://github.com/otaithleigh/opsmodelviewer
Author: Peter Talley
Author-email: ptalley2@vols.utk.edu
License: UNKNOWN
Platform: UNKNOWN
Classifier: Programming Language :: Python :: 3
Classifier: License :: OSI Approved :: MIT License
Classifier: Operating System :: OS Independent
Classifier: Topic :: Scientific/Engineering :: Visualization
Requires-Python: >=3.6
Requires-Dist: bokeh (>=2.0)
Requires-Dist: pandas
